pysnow/__init__.py
pysnow/attachment.py
pysnow/client.py
pysnow/criterion.py
pysnow/enums.py
pysnow/exceptions.py
pysnow/legacy_exceptions.py
pysnow/legacy_request.py
pysnow/oauth_client.py
pysnow/params_builder.py
pysnow/query_builder.py
pysnow/request.py
pysnow/resource.py
pysnow/response.py
pysnow/url_builder.py
pysnow-0.7.17.dist-info/LICENSE
pysnow-0.7.17.dist-info/WHEEL
pysnow-0.7.17.dist-info/METADATA
pysnow-0.7.17.dist-info/RECORD
