Metadata-Version: 2.1
Name: pysnow
Version: 0.7.17
Summary: ServiceNow HTTP client library
Home-page: https://github.com/rbw/pysnow
License: MIT
Author: Robert Wikman
Author-email: rbw@vault13.org
Requires-Python: >=2.7, !=3.0.*, !=3.1.*, !=3.2.*, !=3.3.*, !=3.4.*
Classifier: License :: OSI Approved :: MIT License
Classifier: Programming Language :: Python :: 2
Classifier: Programming Language :: Python :: 2.7
Classifier: Programming Language :: Python :: 3
Classifier: Programming Language :: Python :: 3.5
Classifier: Programming Language :: Python :: 3.6
Classifier: Programming Language :: Python :: 3.7
Classifier: Programming Language :: Python :: 3.8
Classifier: Programming Language :: Python :: 3.9
Requires-Dist: ijson (>=2.5.1,<3.0.0)
Requires-Dist: oauthlib (>=3.1.0,<4.0.0)
Requires-Dist: python-magic (>=0.4.15,<0.5.0)
Requires-Dist: pytz (>=2019.3,<2020.0)
Requires-Dist: requests (>=2.21.0,<3.0.0)
Requires-Dist: requests-oauthlib (>=1.3.0,<2.0.0)
Requires-Dist: six (>=1.13.0,<2.0.0)
